cinetica/__init__.py
cinetica/config.py
cinetica/logger.py
cinetica/optimizacion.py
cinetica/units.py
cinetica/cinematica/__init__.py
cinetica/cinematica/base_movimiento.py
cinetica/cinematica/circular/__init__.py
cinetica/cinematica/circular/movimiento_circular_uniforme.py
cinetica/cinematica/circular/movimiento_circular_uniformemente_variado.py
cinetica/cinematica/espacial/__init__.py
cinetica/cinematica/espacial/movimiento_espacial.py
cinetica/cinematica/oscilatorio/__init__.py
cinetica/cinematica/oscilatorio/movimiento_armonico_complejo.py
cinetica/cinematica/oscilatorio/movimiento_armonico_simple.py
cinetica/cinematica/parabolico/__init__.py
cinetica/cinematica/parabolico/analisis.py
cinetica/cinematica/parabolico/base.py
cinetica/cinematica/rectilineo/__init__.py
cinetica/cinematica/rectilineo/movimiento_rectilineo_uniforme.py
cinetica/cinematica/rectilineo/movimiento_rectilineo_uniformemente_variado.py
cinetica/cinematica/rectilineo/mruv_optimizado.py
cinetica/cinematica/relativo/__init__.py
cinetica/cinematica/relativo/velocidad_relativa.py
cinetica/dinamica/__init__.py
cinetica/dinamica/choques.py
cinetica/dinamica/fuerzas.py
cinetica/dinamica/gravitacion.py
cinetica/dinamica/newton.py
cinetica/dinamica/sistemas_particulas.py
cinetica/dinamica/trabajo_energia.py
cinetica/dinamica/rotacional/__init__.py
cinetica/dinamica/rotacional/cuerpos_rigidos.py
cinetica/dinamica/rotacional/ecuaciones_euler.py
cinetica/dinamica/rotacional/energia_rotacional.py
cinetica/dinamica/rotacional/momento_angular.py
cinetica/dinamica/rotacional/torque.py
cinetica/graficos/__init__.py
cinetica-0.26.0.dist-info/licenses/LICENSE
cinetica-0.26.0.dist-info/METADATA
cinetica-0.26.0.dist-info/WHEEL
cinetica-0.26.0.dist-info/top_level.txt
cinetica-0.26.0.dist-info/RECORD
