Metadata-Version: 2.4
Name: cinetica
Version: 0.26.0
Summary: A Python library for physics modules.
Author-email: Elabsurdo984 <matiassfernandez00@gmail.com>
License: MIT License
Project-URL: Source Code, https://github.com/Elabsurdo984/Cinetica
Project-URL: Documentation, https://github.com/Elabsurdo984/Cinetica/blob/master/DOCS.md
Project-URL: Changelog, https://github.com/Elabsurdo984/Cinetica/blob/master/CHANGELOG.md
Project-URL: Bug Tracker, https://github.com/Elabsurdo984/Cinetica/issues
Keywords: physics,library,science
Classifier: Programming Language :: Python :: 3
Classifier: License :: OSI Approved :: MIT License
Classifier: Operating System :: OS Independent
Classifier: Development Status :: 3 - Alpha
Classifier: Intended Audience :: Science/Research
Classifier: Topic :: Scientific/Engineering :: Physics
Requires-Python: >=3.11
License-File: LICENSE
Requires-Dist: numpy>=2.3.2
Requires-Dist: matplotlib>=3.10.5
Requires-Dist: pint>=0.23
Requires-Dist: pydantic>=2.0.0
Requires-Dist: python-dotenv>=1.0.0
Requires-Dist: numba>=0.61.2
Provides-Extra: dev
Requires-Dist: pytest>=7.0.0; extra == "dev"
Requires-Dist: pytest-cov>=4.0.0; extra == "dev"
Requires-Dist: pytest-mock>=3.10.0; extra == "dev"
Requires-Dist: pytest-env>=1.1.3; extra == "dev"
Requires-Dist: hypothesis>=6.0.0; extra == "dev"
Requires-Dist: black>=23.0.0; extra == "dev"
Requires-Dist: flake8>=6.0.0; extra == "dev"
Requires-Dist: mypy>=1.0.0; extra == "dev"
Requires-Dist: pre-commit>=3.0.0; extra == "dev"
Requires-Dist: twine>=4.0.0; extra == "dev"
Requires-Dist: build>=0.10.0; extra == "dev"
Requires-Dist: types-python-dateutil>=2.8.0; extra == "dev"
Requires-Dist: types-requests>=2.28.0; extra == "dev"
Dynamic: license-file
